odoo/addons/web_disable_export_group/README.rst
odoo/addons/web_disable_export_group/__init__.py
odoo/addons/web_disable_export_group/__manifest__.py
odoo/addons/web_disable_export_group/i18n/ca.po
odoo/addons/web_disable_export_group/i18n/de.po
odoo/addons/web_disable_export_group/i18n/es.po
odoo/addons/web_disable_export_group/i18n/fr.po
odoo/addons/web_disable_export_group/i18n/hr.po
odoo/addons/web_disable_export_group/i18n/pt.po
odoo/addons/web_disable_export_group/i18n/pt_BR.po
odoo/addons/web_disable_export_group/i18n/tr.po
odoo/addons/web_disable_export_group/i18n/web_disable_export_group.pot
odoo/addons/web_disable_export_group/i18n/zh_CN.po
odoo/addons/web_disable_export_group/models/__init__.py
odoo/addons/web_disable_export_group/models/ir_http.py
odoo/addons/web_disable_export_group/readme/CONFIGURE.rst
odoo/addons/web_disable_export_group/readme/CONTRIBUTORS.rst
odoo/addons/web_disable_export_group/readme/DESCRIPTION.rst
odoo/addons/web_disable_export_group/readme/USAGE.rst
odoo/addons/web_disable_export_group/security/groups.xml
odoo/addons/web_disable_export_group/static/description/icon.png
odoo/addons/web_disable_export_group/static/description/index.html
odoo/addons/web_disable_export_group/static/src/js/disable_export_group.js
odoo/addons/web_disable_export_group/templates/assets.xml
odoo/addons/web_disable_export_group/tests/__init__.py
odoo/addons/web_disable_export_group/tests/test_disable_export_group.py
odoo12_addon_web_disable_export_group-12.0.1.0.0.99.dev28.dist-info/METADATA
odoo12_addon_web_disable_export_group-12.0.1.0.0.99.dev28.dist-info/WHEEL
odoo12_addon_web_disable_export_group-12.0.1.0.0.99.dev28.dist-info/top_level.txt
odoo12_addon_web_disable_export_group-12.0.1.0.0.99.dev28.dist-info/RECORD
